[
  {
    "line": 2,
    "elements": [
      {
        "start_timestamp": "2020-01-06T18:59:02.908Z",
        "before": [
          {
            "result": {
              "duration": 5432220300,
              "status": "passed"
            },
            "match": {
              "location": "Hook.setup()"
            }
          }
        ],
        "line": 13,
        "name": "Create a new contact",
        "description": "",
        "id": "contacts-page-testing;create-a-new-contact",
        "after": [
          {
            "result": {
              "duration": 939680200,
              "status": "passed"
            },
            "match": {
              "location": "Hook.teardown(Scenario)"
            }
          }
        ],
        "type": "scenario",
        "keyword": "Scenario",
        "steps": [
          {
            "result": {
              "duration": 1994122200,
              "status": "passed"
            },
            "line": 14,
            "name": "user is on the login page",
            "match": {
              "location": "ContactsStepDefinitions.user_is_on_the_login_page()"
            },
            "keyword": "Given "
          },
          {
            "result": {
              "duration": 2411796300,
              "status": "passed"
            },
            "line": 15,
            "name": "user logs in as inventory_manager",
            "match": {
              "location": "ContactsStepDefinitions.user_logs_in_as_inventory_manager()"
            },
            "keyword": "And "
          },
          {
            "result": {
              "duration": 3510158200,
              "status": "passed"
            },
            "line": 16,
            "name": "user navigates to Contacts module",
            "match": {
              "location": "ContactsStepDefinitions.user_navigates_to_module()"
            },
            "keyword": "Then "
          },
          {
            "result": {
              "duration": 6486494300,
              "status": "passed"
            },
            "line": 17,
            "name": "checkbox is selected",
            "match": {
              "location": "ContactsStepDefinitions.checkbox_is_selected()"
            },
            "keyword": "And "
          }
        ],
        "tags": [
          {
            "name": "@contacts_page"
          },
          {
            "name": "@checkbox"
          }
        ]
      }
    ],
    "name": "Contacts page testing",
    "description": "",
    "id": "contacts-page-testing",
    "keyword": "Feature",
    "uri": "file:src/test/resources/features/contacts_module/Contacts.feature",
    "tags": [
      {
        "name": "@contacts_page",
        "type": "Tag",
        "location": {
          "line": 1,
          "column": 1
        }
      }
    ]
  }
]